{
  "temperature": 25.8,
  "humidity": 58.0,
  "set_temperature": 28,
  "updated_at": "2026-07-03T18:45:16.102965+09:00",
  "history": [
    {
      "time": "16:55",
      "temp": 25.4,
      "hum": 57.0
    },
    {
      "time": "17:00",
      "temp": 25.4,
      "hum": 57.0
    },
    {
      "time": "17:05",
      "temp": 25.4,
      "hum": 57.0
    },
    {
      "time": "17:10",
      "temp": 25.4,
      "hum": 57.0
    },
    {
      "time": "17:15",
      "temp": 25.4,
      "hum": 57.0
    },
    {
      "time": "17:18",
      "temp": 25.4,
      "hum": 57.0
    },
    {
      "time": "17:20",
      "temp": 25.4,
      "hum": 57.0
    },
    {
      "time": "17:25",
      "temp": 25.4,
      "hum": 57.0
    },
    {
      "time": "17:30",
      "temp": 25.4,
      "hum": 57.0
    },
    {
      "time": "17:35",
      "temp": 25.4,
      "hum": 57.0
    },
    {
      "time": "17:40",
      "temp": 25.4,
      "hum": 57.0
    },
    {
      "time": "17:45",
      "temp": 25.4,
      "hum": 57.0
    },
    {
      "time": "17:50",
      "temp": 25.4,
      "hum": 57.0
    },
    {
      "time": "17:55",
      "temp": 25.8,
      "hum": 58.0
    },
    {
      "time": "18:00",
      "temp": 25.8,
      "hum": 58.0
    },
    {
      "time": "18:05",
      "temp": 25.8,
      "hum": 58.0
    },
    {
      "time": "18:10",
      "temp": 25.8,
      "hum": 58.0
    },
    {
      "time": "18:15",
      "temp": 25.8,
      "hum": 58.0
    },
    {
      "time": "18:20",
      "temp": 25.8,
      "hum": 58.0
    },
    {
      "time": "18:25",
      "temp": 25.8,
      "hum": 58.0
    },
    {
      "time": "18:30",
      "temp": 25.8,
      "hum": 58.0
    },
    {
      "time": "18:35",
      "temp": 25.8,
      "hum": 58.0
    },
    {
      "time": "18:40",
      "temp": 25.8,
      "hum": 58.0
    },
    {
      "time": "18:45",
      "temp": 25.8,
      "hum": 58.0
    }
  ]
}