{
  "temperature": 27.1,
  "humidity": 63.0,
  "set_temperature": 28,
  "updated_at": "2026-07-12T04:20:35.757792+09:00",
  "history": [
    {
      "time": "02:30",
      "temp": 27.2,
      "hum": 63.0
    },
    {
      "time": "02:35",
      "temp": 27.2,
      "hum": 63.0
    },
    {
      "time": "02:40",
      "temp": 27.2,
      "hum": 63.0
    },
    {
      "time": "02:45",
      "temp": 27.2,
      "hum": 63.0
    },
    {
      "time": "02:50",
      "temp": 27.2,
      "hum": 63.0
    },
    {
      "time": "02:55",
      "temp": 27.1,
      "hum": 63.0
    },
    {
      "time": "03:00",
      "temp": 27.1,
      "hum": 63.0
    },
    {
      "time": "03:05",
      "temp": 27.1,
      "hum": 63.0
    },
    {
      "time": "03:10",
      "temp": 27.1,
      "hum": 63.0
    },
    {
      "time": "03:15",
      "temp": 27.1,
      "hum": 63.0
    },
    {
      "time": "03:20",
      "temp": 27.1,
      "hum": 63.0
    },
    {
      "time": "03:25",
      "temp": 27.1,
      "hum": 63.0
    },
    {
      "time": "03:30",
      "temp": 27.1,
      "hum": 63.0
    },
    {
      "time": "03:35",
      "temp": 27.1,
      "hum": 63.0
    },
    {
      "time": "03:37",
      "temp": 27.1,
      "hum": 63.0
    },
    {
      "time": "03:40",
      "temp": 27.1,
      "hum": 63.0
    },
    {
      "time": "03:45",
      "temp": 27.1,
      "hum": 63.0
    },
    {
      "time": "03:50",
      "temp": 27.1,
      "hum": 63.0
    },
    {
      "time": "03:55",
      "temp": 27.1,
      "hum": 63.0
    },
    {
      "time": "04:00",
      "temp": 27.1,
      "hum": 63.0
    },
    {
      "time": "04:05",
      "temp": 27.1,
      "hum": 63.0
    },
    {
      "time": "04:10",
      "temp": 27.1,
      "hum": 63.0
    },
    {
      "time": "04:15",
      "temp": 27.1,
      "hum": 63.0
    },
    {
      "time": "04:20",
      "temp": 27.1,
      "hum": 63.0
    }
  ]
}