{
  "temperature": 25.6,
  "humidity": 62.0,
  "set_temperature": 28,
  "updated_at": "2026-07-01T10:35:12.356513+09:00",
  "history": [
    {
      "time": "08:45",
      "temp": 25.6,
      "hum": 68.0
    },
    {
      "time": "08:50",
      "temp": 25.6,
      "hum": 68.0
    },
    {
      "time": "08:55",
      "temp": 25.8,
      "hum": 67.0
    },
    {
      "time": "09:00",
      "temp": 25.8,
      "hum": 67.0
    },
    {
      "time": "09:05",
      "temp": 25.8,
      "hum": 67.0
    },
    {
      "time": "09:10",
      "temp": 25.8,
      "hum": 67.0
    },
    {
      "time": "09:12",
      "temp": 25.8,
      "hum": 67.0
    },
    {
      "time": "09:15",
      "temp": 25.8,
      "hum": 67.0
    },
    {
      "time": "09:20",
      "temp": 25.8,
      "hum": 67.0
    },
    {
      "time": "09:25",
      "temp": 25.8,
      "hum": 67.0
    },
    {
      "time": "09:30",
      "temp": 25.8,
      "hum": 67.0
    },
    {
      "time": "09:35",
      "temp": 25.8,
      "hum": 67.0
    },
    {
      "time": "09:40",
      "temp": 25.8,
      "hum": 67.0
    },
    {
      "time": "09:45",
      "temp": 25.8,
      "hum": 67.0
    },
    {
      "time": "09:50",
      "temp": 25.8,
      "hum": 67.0
    },
    {
      "time": "09:55",
      "temp": 25.6,
      "hum": 62.0
    },
    {
      "time": "10:00",
      "temp": 25.6,
      "hum": 62.0
    },
    {
      "time": "10:05",
      "temp": 25.6,
      "hum": 62.0
    },
    {
      "time": "10:10",
      "temp": 25.6,
      "hum": 62.0
    },
    {
      "time": "10:15",
      "temp": 25.6,
      "hum": 62.0
    },
    {
      "time": "10:20",
      "temp": 25.6,
      "hum": 62.0
    },
    {
      "time": "10:25",
      "temp": 25.6,
      "hum": 62.0
    },
    {
      "time": "10:30",
      "temp": 25.6,
      "hum": 62.0
    },
    {
      "time": "10:35",
      "temp": 25.6,
      "hum": 62.0
    }
  ]
}